Metadata-Version: 2.1
Name: random-tunnel
Version: 0.1.1
Summary: Create random tunnel on each new connection.
Home-page: https://github.com/turbo-tunnel/random-tunnel
Author: drunkdream
Author-email: drunkdream@qq.com
License: MIT
Platform: UNKNOWN
Classifier: Development Status :: 3 - Alpha
Classifier: License :: OSI Approved :: MIT License
Classifier: Programming Language :: Python
Classifier: Programming Language :: Python :: 3
Classifier: Programming Language :: Python :: 3.5
Classifier: Programming Language :: Python :: 3.6
Classifier: Programming Language :: Python :: 3.7
Classifier: Programming Language :: Python :: 3.8
Classifier: Intended Audience :: Developers
Requires-Python: >=3.5
